jetsim-0.0.1.dist-info/METADATA
jetsim-0.0.1.dist-info/WHEEL
jetsim-0.0.1.dist-info/licenses/LICENSE
jetsim/__init__.py
jetsim/jetsim.cpython-313-darwin.so
jetsim-0.0.1.dist-info/RECORD
