Metadata-Version: 2.4
Name: jetsim
Version: 0.0.1
Classifier: Development Status :: 1 - Planning
Classifier: License :: OSI Approved :: MIT License
Classifier: Programming Language :: Rust
Classifier: Programming Language :: Python :: Implementation :: CPython
Classifier: Programming Language :: Python :: 3.9
Classifier: Programming Language :: Python :: 3.10
Classifier: Programming Language :: Python :: 3.11
Classifier: Programming Language :: Python :: 3.12
Classifier: Programming Language :: Python :: 3.13
Classifier: Topic :: Scientific/Engineering
License-File: LICENSE
Summary: Fast air traffic simulator - Python bindings
Keywords: simulation,aviation,air-traffic,atc
License: MIT
Requires-Python: >=3.9
Project-URL: Repository, https://github.com/open-aviation/jetsim
